intermat/__init__.py
intermat/alignn_anderson.py
intermat/analyze.py
intermat/calculators.py
intermat/config.py
intermat/ewald.py
intermat/generate.py
intermat/master.py
intermat/p.py
intermat/run_intermat.py
intermat/surf_andersen.py
intermat/data/__init__.py
intermat/data/classify.py
intermat-2024.3.24.data/scripts/run_intermat.py
intermat-2024.3.24.dist-info/LICENSE.rst
intermat-2024.3.24.dist-info/METADATA
intermat-2024.3.24.dist-info/WHEEL
intermat-2024.3.24.dist-info/top_level.txt
intermat-2024.3.24.dist-info/RECORD
