Metadata-Version: 2.1
Name: intermat
Version: 2024.3.24
Summary: intermat
Home-page: https://github.com/usnistgov/intermat
Author: Kamal Choudhary
Author-email: kamal.choudhary@nist.gov
License: UNKNOWN
Platform: UNKNOWN
Classifier: Programming Language :: Python :: 3
Classifier: License :: OSI Approved :: MIT License
Classifier: Operating System :: OS Independent
Requires-Python: >=3.8
License-File: LICENSE.rst
